ms_reader/__init__.py
ms_reader/__main__.py
ms_reader/app.py
ms_reader/extract.py
ms_reader/skyline_convert.py
ms_reader/utils.py
ms_reader-1.8.0.dist-info/licenses/LICENSE
ms_reader-1.8.0.dist-info/METADATA
ms_reader-1.8.0.dist-info/WHEEL
ms_reader-1.8.0.dist-info/entry_points.txt
ms_reader-1.8.0.dist-info/top_level.txt
ms_reader-1.8.0.dist-info/RECORD
