Metadata-Version: 2.4
Name: ms_reader
Version: 1.8.0
Summary: Package for parsing a Tracefinder or Skyline file containing processed Mass Spectrometry data
Home-page: https://github.com/llegregam/MSReader
Author: Loïc Le Grégam
Author-email: legregam@insa-toulouse.fr
Project-URL: Bug Tracker, https://github.com/llegregam/MSReader/issues
Classifier: Programming Language :: Python :: 3
Classifier: License :: OSI Approved :: GNU General Public License (GPL)
Classifier: Operating System :: OS Independent
Requires-Python: >=3.8
License-File: LICENSE
Requires-Dist: pandas>=2.0.3
Requires-Dist: numpy>=1.21.4
Requires-Dist: natsort>=8.0.0
Requires-Dist: streamlit>=1.8.0
Requires-Dist: openpyxl>=3.1.0
Provides-Extra: testing
Requires-Dist: pytest>=7.1.2; extra == "testing"
Requires-Dist: flake8>=4.0.1; extra == "testing"
Requires-Dist: tox>=3.25.0; extra == "testing"
Dynamic: license-file
